README.md
setup.py
PyWaifu.egg-info/PKG-INFO
PyWaifu.egg-info/SOURCES.txt
PyWaifu.egg-info/dependency_links.txt
PyWaifu.egg-info/top_level.txt
pywaifu/__init__.py
pywaifu/choose.py
pywaifu/waifu_api.py