Metadata-Version: 2.1
Name: PyWaifu
Version: 1.0.1
Summary: PyWaifu is a simple package that shows cute waifus
Home-page: https://github.com/DragonSphere02/PyWaifu
Author: DragonSh
Author-email: isaiasfb8@gmail.com
License: MIT
Keywords: waifu discord bots
Platform: UNKNOWN
Classifier: License :: OSI Approved :: MIT License
Classifier: Operating System :: OS Independent
Classifier: Development Status :: 4 - Beta
Classifier: Natural Language :: English
Classifier: Programming Language :: Python :: 3
Classifier: Topic :: Internet
